<?xml version="1.0" encoding="UTF-8"?>
<objects serializationModel="Studio.02.03.00">
	<object class="AudioFile" id="{8abe815a-7160-4640-a92a-f4c29daf4eb9}">
		<property name="assetPath">
			<value>InGameSounds/GarbageThrowing.wav</value>
		</property>
		<property name="frequencyInKHz">
			<value>96</value>
		</property>
		<property name="channelCount">
			<value>2</value>
		</property>
		<property name="length">
			<value>0.2578125</value>
		</property>
		<relationship name="masterAssetFolder">
			<destination>{906d033d-bea9-4bad-b245-a9a6db12ac22}</destination>
		</relationship>
	</object>
</objects>
